CTpackage/Cartoonmodule1.py
CTpackage/__init__.py
ctpackage-0.1.1.dist-info/METADATA
ctpackage-0.1.1.dist-info/WHEEL
ctpackage-0.1.1.dist-info/top_level.txt
ctpackage-0.1.1.dist-info/RECORD
