Metadata-Version: 2.4
Name: CTpackage
Version: 0.1.1
Summary: This my first package. Can use to calculate area, length of circle and area of a sector of a circle
Home-page: https://github.com/Cartoonmee/CTpackage
Author: THITIRAT
Author-email: thitirat98242@gmail.com
Requires-Python: >=3.7
Dynamic: author
Dynamic: author-email
Dynamic: description
Dynamic: description-content-type
Dynamic: home-page
Dynamic: requires-python
Dynamic: summary
